SudokuSolverPython/SudokuSolverPython.py
SudokuSolverPython/__init__.py
tests/__init__.py
tests/test_SudokuSolverPython.py
SudokuSolverPython-0.3.0.dist-info/METADATA
SudokuSolverPython-0.3.0.dist-info/WHEEL
SudokuSolverPython-0.3.0.dist-info/top_level.txt
SudokuSolverPython-0.3.0.dist-info/RECORD
