Metadata-Version: 2.1
Name: SudokuSolverPython
Version: 0.3.0
Summary: Python library Sudoku Solver
Author: dkkobzev
Author-email: dima.kobzev05@mail.ru
Classifier: Programming Language :: Python :: 3
Classifier: License :: OSI Approved :: MIT License
